{
  "MonoBehaviour": {
    "m_ObjectHideFlags": 0,
    "m_CorrespondingSourceObject": {
      "fileID": 0
    },
    "m_PrefabInstance": {
      "fileID": 0
    },
    "m_PrefabAsset": {
      "fileID": 0
    },
    "m_GameObject": {
      "fileID": 0
    },
    "m_Enabled": 1,
    "m_EditorHideFlags": 0,
    "m_Script": {
      "fileID": 11500000,
      "guid": "353d3699e795a4f5b9c3a521ef46f9e1",
      "type": 3
    },
    "m_Name": "accessory_machines_c_0011_03",
    "m_EditorClassIdentifier": null,
    "aircraftName": "パン・ダー・フリーダム",
    "description": "パンダの手",
    "moveSpeed": 22,
    "moveAccel": 28,
    "moveResistPower": 35,
    "moveBrake": 30,
    "rotationSpeed": 360,
    "respawnPositionSelectMoveSpeed": 80,
    "defense": 20,
    "searchHitRadius": 1,
    "weaponPositionOffset": {
      "x": 0,
      "y": 2.38,
      "z": 4.72
    },
    "pilotPositionOffset": {
      "x": 0,
      "y": 3.29,
      "z": 0.66
    },
    "pilotScale": {
      "x": 3,
      "y": 3,
      "z": 3
    },
    "avatarNeckPositionOffset": {
      "x": 0,
      "y": 6.5,
      "z": 0.1
    },
    "avatarScale": {
      "x": 14,
      "y": 14,
      "z": 14
    },
    "weaponSettings": {
      "fileID": 11400000,
      "guid": "be1db1649d5262541836d7fcc59d188d",
      "type": 2
    },
    "passiveSkills": [],
    "resistantToBuffs": null,
    "flickDashSettings": {
      "fileID": 0
    },
    "ForceShowFlyGauge": 0
  }
}