{
  "aircraftName": "S44",
  "description": null,
  "moveSpeed": 34,
  "moveAccel": 28,
  "moveResistPower": 40,
  "moveBrake": 45,
  "rotationSpeed": 720,
  "respawnPositionSelectMoveSpeed": 80,
  "defense": 19,
  "searchHitRadius": 1,
  "weaponPositionOffset": {
    "x": 0,
    "y": 0.6,
    "z": 4
  },
  "pilotPositionOffset": {
    "x": -4.543419e-13,
    "y": 1.0233241,
    "z": -3.239134
  },
  "pilotScale": {
    "x": 3.2,
    "y": 3.2,
    "z": 3.2
  },
  "avatarNeckPositionOffset": {
    "x": 0.0032000002,
    "y": 4.411228,
    "z": -4.080113
  },
  "avatarScale": {
    "x": 14,
    "y": 14,
    "z": 14
  },
  "ForceShowFlyGauge": 0,
  "weaponSettings": {
    "m_ObjectHideFlags": 0,
    "m_CorrespondingSourceObject": {
      "fileID": 0
    },
    "m_PrefabInstance": {
      "fileID": 0
    },
    "m_PrefabAsset": {
      "fileID": 0
    },
    "m_GameObject": {
      "fileID": 0
    },
    "m_Enabled": 1,
    "m_EditorHideFlags": 0,
    "m_Script": {
      "fileID": 11500000,
      "guid": "3b98b1f3a243a5f56eb904d05b070f77",
      "type": 3
    },
    "m_Name": "wp_multiswing",
    "m_EditorClassIdentifier": null,
    "memo": "S44",
    "weaponCategry": 1,
    "enemySearchRadius": 14,
    "enemySearchOffset": 10,
    "attackPower": 51,
    "attackStopPower": 10000,
    "attackIgnoreDefense": 0,
    "attackDisableBrakeTime": 1,
    "additionalPower": 0,
    "attackHitShape": 0,
    "attackHitRadius": 5,
    "attackHitSize": {
      "x": 0,
      "y": 0,
      "z": 0
    },
    "hitGrowingTimeRate": 0,
    "attackHitPositionOffset": {
      "x": 0,
      "y": 0,
      "z": 0
    },
    "attackMoveSpeed": 0,
    "attackMoveAccel": 0,
    "attackMoveSpeedY": 0,
    "attackMoveAccelY": 0,
    "attackDuration": 0.5,
    "attackTimeSpan": 1.5,
    "isBackCritical": 0,
    "isSideCritical": 0,
    "shieldBreak": 0,
    "isReflector": 0,
    "refrectionRate": 0,
    "reflectionAddSpeedRate": 0,
    "invalidRefrection": 0,
    "isSelfRefrection": 0,
    "selfRefrectionNum": 0,
    "refrectionRandomRot": {
      "x": 0,
      "y": 0
    },
    "isHideHitEffect": 0,
    "killComboRate": 0,
    "useLimitMax": -1,
    "spriteButtonIcon": {
      "fileID": 0
    },
    "useClickWhenFire": 1,
    "useChargeWhenFire": 0,
    "useChargeWithoutFire": 0,
    "weaponAutoChargeSettings": {
      "fileID": 0
    },
    "PunchPrefab": {
      "fileID": 1012401758926942,
      "guid": "e2303f69bf9ea11409d0ec6115193ffd",
      "type": 2
    },
    "SmokeFxPrefab": {
      "fileID": 1461815851721609,
      "guid": "7de48b57674bd674eb52329f9ecb5bb8",
      "type": 2
    },
    "SmokeFxLocalPos": {
      "x": 0,
      "y": 0,
      "z": 0
    },
    "Punches": [
      {
        "BaseDegY": 0,
        "SwingDegY": 60
      },
      {
        "BaseDegY": -90,
        "SwingDegY": 60
      },
      {
        "BaseDegY": 90,
        "SwingDegY": 60
      }
    ],
    "Combos": [
      {
        "PunchIndices": 0,
        "ScaleUpRate": 0
      },
      {
        "PunchIndices": 262144,
        "ScaleUpRate": 0
      },
      {
        "PunchIndices": 262144,
        "ScaleUpRate": 0.5
      },
      {
        "PunchIndices": 4398047035392,
        "ScaleUpRate": 0.5
      },
      {
        "PunchIndices": 4398047035392,
        "ScaleUpRate": 1.5
      }
    ],
    "PunchData": {
      "Enabled": 1,
      "MoveRange": 7,
      "AttackScaleAnimOffset": 0,
      "Prefab_Spring": {
        "fileID": 0
      },
      "SpringScaleXY": 0.6,
      "SpringScaleZAdjuster": 0.1,
      "ShootSeType": 55,
      "ShootSeOctaRange": {
        "x": 0,
        "y": 2
      },
      "FireAnimDuration": 1,
      "ReturnAnimDuration": 0.3,
      "AnimatorStateName_Attack": "Attack",
      "UseSameFireId": 0,
      "DontReturn": 0
    },
    "PunchOnChargeMax": 1,
    "BuffTag": "S44MachineMultiSwing",
    "BreakShieldAndRemoveBuffsRatio": 15,
    "RemoveTargetBuffs": [
      {
        "Memo": "ビリビリエナジー",
        "CheckBuffType": 1,
        "BuffType": 30,
        "CheckBuffTag": 0,
        "BuffTag": null
      },
      {
        "Memo": "クラクラエナジー",
        "CheckBuffType": 1,
        "BuffType": 42,
        "CheckBuffTag": 0,
        "BuffTag": null
      },
      {
        "Memo": "初夢カイト",
        "CheckBuffType": 0,
        "BuffType": 0,
        "CheckBuffTag": 1,
        "BuffTag": "SpeedKite"
      },
      {
        "Memo": "応援ラッパ",
        "CheckBuffType": 0,
        "BuffType": 0,
        "CheckBuffTag": 1,
        "BuffTag": "WarCry"
      },
      {
        "Memo": "千客万来キューブ",
        "CheckBuffType": 0,
        "BuffType": 0,
        "CheckBuffTag": 1,
        "BuffTag": "BuffTileDefenseUp"
      },
      {
        "Memo": "とうめいタヌキなどの透明化",
        "CheckBuffType": 1,
        "BuffType": 21,
        "CheckBuffTag": 0,
        "BuffTag": null
      },
      {
        "Memo": "小槌のスピードアップ",
        "CheckBuffType": 1,
        "BuffType": 43,
        "CheckBuffTag": 0,
        "BuffTag": null
      },
      {
        "Memo": "小槌の重さアップ",
        "CheckBuffType": 1,
        "BuffType": 44,
        "CheckBuffTag": 0,
        "BuffTag": null
      },
      {
        "Memo": "小槌の攻撃アップ",
        "CheckBuffType": 1,
        "BuffType": 6,
        "CheckBuffTag": 1,
        "BuffTag": "KoduchiBuffNotUpdate"
      }
    ],
    "MoveAnger": {
      "StartBulletNum": 0,
      "MaxBulletNum": 1,
      "AngerAmountOnMaxBulletNum": 1,
      "FirstBulletReloadSec": 0,
      "FxOnMaxBulletNum": "Fx/Bullet/bl_electric_missile_explosion",
      "SeOnMaxBulletNum": 50,
      "SwitchLocatorTarget": 2
    },
    "BreakShieldAndRemoveBuffsByMissile": 1,
    "MissileSettings": {
      "fileID": 11400000,
      "guid": "73f81e84f498fc54e9f0fde45ee87b5f",
      "type": 2
    }
  },
  "passiveSkills": [
    {
      "m_ObjectHideFlags": 0,
      "m_CorrespondingSourceObject": {
        "fileID": 0
      },
      "m_PrefabInstance": {
        "fileID": 0
      },
      "m_PrefabAsset": {
        "fileID": 0
      },
      "m_GameObject": {
        "fileID": 0
      },
      "m_Enabled": 1,
      "m_EditorHideFlags": 0,
      "m_Script": {
        "fileID": 11500000,
        "guid": "c5b52ff9f8d7db766ccee58c9e65b8e1",
        "type": 3
      },
      "m_Name": "ps_move_accumulate_s44",
      "m_EditorClassIdentifier": null,
      "memo": "移動により強化されていく（2.2秒毎）",
      "weaponCategry": 0,
      "enemySearchRadius": 0,
      "enemySearchOffset": 0,
      "attackPower": 2.2,
      "attackStopPower": 0,
      "attackIgnoreDefense": 0,
      "attackDisableBrakeTime": 0,
      "additionalPower": 0,
      "attackHitShape": 0,
      "attackHitRadius": 0,
      "attackHitSize": {
        "x": 0,
        "y": 0,
        "z": 0
      },
      "hitGrowingTimeRate": 0,
      "attackHitPositionOffset": {
        "x": 0,
        "y": 0,
        "z": 0
      },
      "attackMoveSpeed": 0,
      "attackMoveAccel": 0,
      "attackMoveSpeedY": 0,
      "attackMoveAccelY": 0,
      "attackDuration": -1,
      "attackTimeSpan": 0,
      "isBackCritical": 0,
      "isSideCritical": 0,
      "shieldBreak": 0,
      "isReflector": 0,
      "refrectionRate": 0,
      "reflectionAddSpeedRate": 0,
      "invalidRefrection": 0,
      "isSelfRefrection": 0,
      "selfRefrectionNum": 0,
      "refrectionRandomRot": {
        "x": 0,
        "y": 0
      },
      "isHideHitEffect": 0,
      "killComboRate": 0,
      "useLimitMax": -1,
      "spriteButtonIcon": {
        "fileID": 0
      },
      "useClickWhenFire": 1,
      "useChargeWhenFire": 0,
      "useChargeWithoutFire": 0,
      "weaponAutoChargeSettings": {
        "fileID": 0
      },
      "buffType": 37,
      "targetType": 0,
      "tag": null,
      "powerScaleType": 0,
      "shootSeType": 0,
      "shootAnimName": null,
      "shootFx": null,
      "triggerType": 0,
      "triggerValue": 0,
      "triggerString": null,
      "gradeType": 0,
      "maxGradeNum": 0,
      "remainingLifeBuffSettings": {
        "RemainLife3Power": 0,
        "RemainLife2Power": 0,
        "RemainLife1Power": 0
      },
      "shouldPlayParticleWhenEmitBuff": 1
    }
  ],
  "flickDashSettings": {
    "m_ObjectHideFlags": 0,
    "m_CorrespondingSourceObject": {
      "fileID": 0
    },
    "m_PrefabInstance": {
      "fileID": 0
    },
    "m_PrefabAsset": {
      "fileID": 0
    },
    "m_GameObject": {
      "fileID": 0
    },
    "m_Enabled": 1,
    "m_EditorHideFlags": 0,
    "m_Script": {
      "fileID": 11500000,
      "guid": "fd6d21e32245f8670158d47df2369f83",
      "type": 3
    },
    "m_Name": "FlickDash_0046",
    "m_EditorClassIdentifier": null,
    "Memo": "s44のフリックダッシュ",
    "Interval": 2,
    "FrontMoveStopPower": 10,
    "FrontMoveForce": 45,
    "MutekiTime": 0,
    "StunTime": 0.25,
    "seType": 81,
    "FlyAfter": 0,
    "FlyAnimation": 0,
    "FlyDuration": 0,
    "ContinuousNum": 1,
    "CanContinuousDuration": 1
  },
  "img": "images/accessory/unit0046_01.PNG"
}